Metadata-Version: 2.4
Name: fogis-api-client-timmyBird
Version: 0.7.4
Summary: A Python client for the FOGIS API (Svensk Fotboll)
Home-page: https://github.com/timmyBird/fogis-api-client
Author: Bartek Svaberg
Author-email: bartek.svaberg@gmail.com
Classifier: Programming Language :: Python :: 3
Classifier: License :: OSI Approved :: MIT License
Classifier: Operating System :: OS Independent
Requires-Python: >=3.7
License-File: LICENSE.txt
Requires-Dist: requests
Requires-Dist: beautifulsoup4
Requires-Dist: flask
Requires-Dist: apispec>=6.0.0
Requires-Dist: flask-swagger-ui
Requires-Dist: marshmallow>=3.26.0
Requires-Dist: psutil
Requires-Dist: jsonschema>=4.17.3
Provides-Extra: dev
Requires-Dist: pytest; extra == "dev"
Requires-Dist: pytest-mock; extra == "dev"
Requires-Dist: pytest-cov; extra == "dev"
Requires-Dist: flake8; extra == "dev"
Requires-Dist: flask-cors; extra == "dev"
Requires-Dist: docker; extra == "dev"
Requires-Dist: pylint; extra == "dev"
Requires-Dist: bandit; extra == "dev"
Requires-Dist: mypy; extra == "dev"
Requires-Dist: types-requests; extra == "dev"
Provides-Extra: mock-server
Requires-Dist: flask; extra == "mock-server"
Requires-Dist: flask-swagger-ui; extra == "mock-server"
Requires-Dist: apispec>=6.0.0; extra == "mock-server"
Requires-Dist: marshmallow>=3.26.0; extra == "mock-server"
Requires-Dist: requests; extra == "mock-server"
Dynamic: author
Dynamic: author-email
Dynamic: classifier
Dynamic: description
Dynamic: description-content-type
Dynamic: home-page
Dynamic: license-file
Dynamic: provides-extra
Dynamic: requires-dist
Dynamic: requires-python
Dynamic: summary
